fputils/__init__.py
fputils/either.py
fputils/either.pyi
fputils/io.py
fputils/io.pyi
fputils/option.py
fputils/option.pyi
fputils/py.typed
fputils_python-0.0.7.dist-info/licenses/LICENSE.txt
fputils_python-0.0.7.dist-info/METADATA
fputils_python-0.0.7.dist-info/WHEEL
fputils_python-0.0.7.dist-info/top_level.txt
fputils_python-0.0.7.dist-info/RECORD
