Metadata-Version: 2.4
Name: fputils-python
Version: 0.0.7
Summary: Utility classes for functional programming in Python
Author: Jason McKinney
License-Expression: MIT
Project-URL: Documentation, https://jason-mckinney.github.io/fputils/
Keywords: functional programming,utility,FP,option,either,effect,io
Classifier: Development Status :: 4 - Beta
Classifier: Programming Language :: Python :: 3
Classifier: Operating System :: OS Independent
Requires-Python: >=3.12
License-File: LICENSE.txt
Dynamic: license-file
